wj_google/__init__.py
wj_google/examples/__init__.py
wj_google/examples/bigquery.py
wj_google/examples/sorage_and_drive.py
wj_google/google_api/Google.py
wj_google/google_api/__init__.py
wj_google/google_api/google_api.py
wj_google/google_cloud/__init__.py
wj_google/google_cloud/atlas_mongo.py
wj_google/google_cloud/cloud_connector.py
wj_google/google_cloud/firestone.py
wj_google/main.py
wj_google/tools/__init__.py
wj_google/tools/files_manage.py
wj_google-0.5.1.dist-info/METADATA
wj_google-0.5.1.dist-info/WHEEL
wj_google-0.5.1.dist-info/RECORD
