Metadata-Version: 2.3
Name: wj-google
Version: 0.5.1
Summary: 
Author: Johan
Author-email: mantimanti89@gmail.com
Requires-Python: >=3.9,<4.0
Classifier: Programming Language :: Python :: 3
Classifier: Programming Language :: Python :: 3.9
Classifier: Programming Language :: Python :: 3.10
Classifier: Programming Language :: Python :: 3.11
Classifier: Programming Language :: Python :: 3.12
Classifier: Programming Language :: Python :: 3.13
Requires-Dist: db-dtypes (>=1.2.0,<2.0.0)
Requires-Dist: firebase-admin (>=6.6.0,<7.0.0)
Requires-Dist: google (>=3.0.0,<4.0.0)
Requires-Dist: google-api-python-client (>=2.121.0,<3.0.0)
Requires-Dist: google-auth-oauthlib (>=1.2.0,<2.0.0)
Requires-Dist: google-cloud-bigquery (>=3.18.0,<4.0.0)
Requires-Dist: google-cloud-storage (>=2.15.0,<3.0.0)
Requires-Dist: pymongo (>=4.10.1,<5.0.0)
Requires-Dist: python-dotenv (>=1.0.1,<2.0.0)
